cowponder/__init__.py
cowponder/__main__.py
cowponder/cowponder.py
cowponder/ponder.py
cowponder-0.1.8.dist-info/METADATA
cowponder-0.1.8.dist-info/WHEEL
cowponder-0.1.8.dist-info/entry_points.txt
cowponder-0.1.8.dist-info/top_level.txt
cowponder-0.1.8.dist-info/RECORD
