Metadata-Version: 2.4
Name: cowponder
Version: 0.1.8
Summary: A simple command that displays randomly selected philosophical thoughts from a cow
Home-page: https://max.xz.ax/cowponder
Author: Max Cai
Keywords: cow philosophical ponder cowponder ascii ascii-art fun
Requires-Python: >=3.6
Requires-Dist: requests
Requires-Dist: platformdirs
Dynamic: author
Dynamic: description
Dynamic: description-content-type
Dynamic: home-page
Dynamic: keywords
Dynamic: requires-dist
Dynamic: requires-python
Dynamic: summary
